jma/__init__.py
jma/client.py
jma/exceptions.py
jma/jmastation.py
jma/response.py
jma/tests/__init__.py
jma/tests/test_response.py
jma_client-0.0.1.dist-info/LICENSE
jma_client-0.0.1.dist-info/METADATA
jma_client-0.0.1.dist-info/WHEEL
jma_client-0.0.1.dist-info/top_level.txt
jma_client-0.0.1.dist-info/RECORD
