Metadata-Version: 2.1
Name: jma-client
Version: 0.0.1
Summary: Download data from Japanese Meteorological Association.
Home-page: https://github.com/dliberat/jma-client
Author: Dan Liberatori
Author-email: daniel.liberatori@gmail.com
License: UNKNOWN
Project-URL: Bug Tracker, https://github.com/dliberat/jma-client/issues
Platform: UNKNOWN
Classifier: Programming Language :: Python :: 3
Classifier: License :: OSI Approved :: MIT License
Classifier: Operating System :: OS Independent
Requires-Python: >=3.6
Requires-Dist: requests
